<annotation>
	<folder>2019_train</folder>
	<filename>016248.jpg</filename>
	<path>/home/gfx/Downloads/2019_train/016248.jpg</path>
	<source>
		<database>Unknown</database>
	</source>
	<size>
		<width>1200</width>
		<height>675</height>
		<depth>3</depth>
	</size>
	<segmented>0</segmented>
	<object>
		<name>Hyundai Santa Fe 2019</name>
		<pose>Unspecified</pose>
		<truncated>0</truncated>
		<difficult>0</difficult>
		<bndbox>
			<xmin>89</xmin>
			<ymin>81</ymin>
			<xmax>1094</xmax>
			<ymax>611</ymax>
		</bndbox>
	</object>
</annotation>
